{"allContent":{"docusaurus-plugin-content-docs":{"default":{"loadedVersions":[{"versionName":"current","label":"Next","banner":null,"badge":false,"noIndex":false,"className":"docs-version-current","path":"/CavrianaCorr_FrontEnd/docs","tagsPath":"/CavrianaCorr_FrontEnd/docs/tags","editUrl":"https://github.com/Pantagrueliste/CavrianaCorr_FrontEnd/tree/main/docs","editUrlLocalized":"https://github.com/Pantagrueliste/CavrianaCorr_FrontEnd/tree/main/i18n/en/docusaurus-plugin-content-docs/current","isLast":true,"routePriority":-1,"sidebarFilePath":"/Users/clementgodbarge/CavrianaCorr_FrontEnd/sidebars.js","contentPath":"/Users/clementgodbarge/CavrianaCorr_FrontEnd/docs","contentPathLocalized":"/Users/clementgodbarge/CavrianaCorr_FrontEnd/i18n/en/docusaurus-plugin-content-docs/current","docs":[{"id":"1568/1568-04-06","title":"Guglielmo Gonzaga (1568-04-06)","description":"[fol. 286r]","source":"@site/docs/1568/1568-04-06.md","sourceDirName":"1568","slug":"/1568/1568-04-06","permalink":"/CavrianaCorr_FrontEnd/docs/1568/1568-04-06","draft":false,"unlisted":false,"editUrl":"https://github.com/Pantagrueliste/CavrianaCorr_FrontEnd/tree/main/docs/1568/1568-04-06.md","tags":[],"version":"current","frontMatter":{"title":"Guglielmo Gonzaga (1568-04-06)","expeditor":"Filippo Cavriana","addressee":"Guglielmo Gonzaga","date":"1568-04-06","placeOfOrigin":"Nevers","archiveRef":"Mantova Archivio di Stato di Mantova, Archivio Gonzaga, b654, fols. 286r-286v"},"sidebar":"tutorialSidebar","previous":{"title":"Introduction","permalink":"/CavrianaCorr_FrontEnd/docs/intro"},"next":{"title":"Aurelio Zibramonti (1568-04-28)","permalink":"/CavrianaCorr_FrontEnd/docs/1568/1568-04-28"}},{"id":"1568/1568-04-28","title":"Aurelio Zibramonti (1568-04-28)","description":"[fol. 288r]","source":"@site/docs/1568/1568-04-28.md","sourceDirName":"1568","slug":"/1568/1568-04-28","permalink":"/CavrianaCorr_FrontEnd/docs/1568/1568-04-28","draft":false,"unlisted":false,"editUrl":"https://github.com/Pantagrueliste/CavrianaCorr_FrontEnd/tree/main/docs/1568/1568-04-28.md","tags":[],"version":"current","frontMatter":{"title":"Aurelio Zibramonti (1568-04-28)","expeditor":"Filippo Cavriana","addressee":"Aurelio Zibramonti","date":"1568-04-28","placeOfOrigin":"Nevers","archiveRef":"Mantua Archivio di Stato di Mantova, Archivio Gonzaga, b654, fols. 288r-289r"},"sidebar":"tutorialSidebar","previous":{"title":"Guglielmo Gonzaga (1568-04-06)","permalink":"/CavrianaCorr_FrontEnd/docs/1568/1568-04-06"},"next":{"title":"Guglielmo Gonzaga (1568-05-04)","permalink":"/CavrianaCorr_FrontEnd/docs/1568/1568-05-04"}},{"id":"1568/1568-05-04","title":"Guglielmo Gonzaga (1568-05-04)","description":"[fol. 290r]","source":"@site/docs/1568/1568-05-04.md","sourceDirName":"1568","slug":"/1568/1568-05-04","permalink":"/CavrianaCorr_FrontEnd/docs/1568/1568-05-04","draft":false,"unlisted":false,"editUrl":"https://github.com/Pantagrueliste/CavrianaCorr_FrontEnd/tree/main/docs/1568/1568-05-04.md","tags":[],"version":"current","frontMatter":{"title":"Guglielmo Gonzaga (1568-05-04)","expeditor":"Filippo Cavriana","addressee":"Guglielmo Gonzaga","date":"1568-05-04","placeOfOrigin":"Nevers","archiveRef":"Mantua Archivio di Stato di Mantovae, Archivio Gonzaga, b654, fols. 290r-291r"},"sidebar":"tutorialSidebar","previous":{"title":"Aurelio Zibramonti (1568-04-28)","permalink":"/CavrianaCorr_FrontEnd/docs/1568/1568-04-28"},"next":{"title":"Guglielmo Gonzaga (1568-05-05)","permalink":"/CavrianaCorr_FrontEnd/docs/1568/1568-05-05"}},{"id":"1568/1568-05-05","title":"Guglielmo Gonzaga (1568-05-05)","description":"[fol. 292r]","source":"@site/docs/1568/1568-05-05.md","sourceDirName":"1568","slug":"/1568/1568-05-05","permalink":"/CavrianaCorr_FrontEnd/docs/1568/1568-05-05","draft":false,"unlisted":false,"editUrl":"https://github.com/Pantagrueliste/CavrianaCorr_FrontEnd/tree/main/docs/1568/1568-05-05.md","tags":[],"version":"current","frontMatter":{"title":"Guglielmo Gonzaga (1568-05-05)","expeditor":"Filippo Cavriana","addressee":"Guglielmo Gonzaga","date":"1568-05-05","placeOfOrigin":"Nevers","archiveRef":"Mantova Archivio di Stato di Mantova, Archivio Gonzaga, b654, fols. 292r-292v"},"sidebar":"tutorialSidebar","previous":{"title":"Guglielmo Gonzaga (1568-05-04)","permalink":"/CavrianaCorr_FrontEnd/docs/1568/1568-05-04"},"next":{"title":"Guglielmo Gonzaga (1568-05-28)","permalink":"/CavrianaCorr_FrontEnd/docs/1568/1568-05-28"}},{"id":"1568/1568-05-28","title":"Guglielmo Gonzaga (1568-05-28)","description":"[fol. 294r]","source":"@site/docs/1568/1568-05-28.md","sourceDirName":"1568","slug":"/1568/1568-05-28","permalink":"/CavrianaCorr_FrontEnd/docs/1568/1568-05-28","draft":false,"unlisted":false,"editUrl":"https://github.com/Pantagrueliste/CavrianaCorr_FrontEnd/tree/main/docs/1568/1568-05-28.md","tags":[],"version":"current","frontMatter":{"title":"Guglielmo Gonzaga (1568-05-28)","expeditor":"Filippo Cavriana","addressee":"Guglielmo Gonzaga","date":"1568-05-28","placeOfOrigin":"Nevers","archiveRef":"Mantua Archivio di Stato di Mantova, Archivio Gonzaga, b654, fols. 294r-294v"},"sidebar":"tutorialSidebar","previous":{"title":"Guglielmo Gonzaga (1568-05-05)","permalink":"/CavrianaCorr_FrontEnd/docs/1568/1568-05-05"},"next":{"title":"Guglielmo Gonzaga (1568-06-09)","permalink":"/CavrianaCorr_FrontEnd/docs/1568/1568-06-09"}},{"id":"1568/1568-06-09","title":"Guglielmo Gonzaga (1568-06-09)","description":"[fol. 296r]","source":"@site/docs/1568/1568-06-09.md","sourceDirName":"1568","slug":"/1568/1568-06-09","permalink":"/CavrianaCorr_FrontEnd/docs/1568/1568-06-09","draft":false,"unlisted":false,"editUrl":"https://github.com/Pantagrueliste/CavrianaCorr_FrontEnd/tree/main/docs/1568/1568-06-09.md","tags":[],"version":"current","frontMatter":{"title":"Guglielmo Gonzaga (1568-06-09)","expeditor":"Filippo Cavriana","addressee":"Guglielmo Gonzaga","date":"1568-06-09","placeOfOrigin":"Nevers","archiveRef":"Mantua Archivio di Stato di Mantova, Archivio Gonzaga, b654, fols. 296r-296v"},"sidebar":"tutorialSidebar","previous":{"title":"Guglielmo Gonzaga (1568-05-28)","permalink":"/CavrianaCorr_FrontEnd/docs/1568/1568-05-28"},"next":{"title":"Guglielmo Gonzaga (1568-07-03)","permalink":"/CavrianaCorr_FrontEnd/docs/1568/1568-07-03"}},{"id":"1568/1568-07-03","title":"Guglielmo Gonzaga (1568-07-03)","description":"[fol. 924r]","source":"@site/docs/1568/1568-07-03.md","sourceDirName":"1568","slug":"/1568/1568-07-03","permalink":"/CavrianaCorr_FrontEnd/docs/1568/1568-07-03","draft":false,"unlisted":false,"editUrl":"https://github.com/Pantagrueliste/CavrianaCorr_FrontEnd/tree/main/docs/1568/1568-07-03.md","tags":[],"version":"current","frontMatter":{"title":"Guglielmo Gonzaga (1568-07-03)","expeditor":"Filippo Cavriana","addressee":"Guglielmo Gonzaga","date":"1568-07-03","placeOfOrigin":"Nevers","archiveRef":"Mantua Archivio di Stato di Mantova, Archivio Gonzaga, b654, fols. 924r-924v"},"sidebar":"tutorialSidebar","previous":{"title":"Guglielmo Gonzaga (1568-06-09)","permalink":"/CavrianaCorr_FrontEnd/docs/1568/1568-06-09"},"next":{"title":"Guglielmo Gonzaga (1568-07-24)","permalink":"/CavrianaCorr_FrontEnd/docs/1568/1568-07-24"}},{"id":"1568/1568-07-24","title":"Guglielmo Gonzaga (1568-07-24)","description":"Illustrissimo Signor  mio.","source":"@site/docs/1568/1568-07-24.md","sourceDirName":"1568","slug":"/1568/1568-07-24","permalink":"/CavrianaCorr_FrontEnd/docs/1568/1568-07-24","draft":false,"unlisted":false,"editUrl":"https://github.com/Pantagrueliste/CavrianaCorr_FrontEnd/tree/main/docs/1568/1568-07-24.md","tags":[],"version":"current","frontMatter":{"title":"Guglielmo Gonzaga (1568-07-24)","expeditor":"Filippo Cavriana","addressee":"Guglielmo Gonzaga","date":"1568-07-24","placeOfOrigin":"Nevers","archiveRef":"Mantua Archivio di Stato di Mantova, Davari Collection,, fols. -"},"sidebar":"tutorialSidebar","previous":{"title":"Guglielmo Gonzaga (1568-07-03)","permalink":"/CavrianaCorr_FrontEnd/docs/1568/1568-07-03"},"next":{"title":"Guglielmo Gonzaga (1568-09-07)","permalink":"/CavrianaCorr_FrontEnd/docs/1568/1568-09-07"}},{"id":"1568/1568-09-07","title":"Guglielmo Gonzaga (1568-09-07)","description":"[fol. 303r]","source":"@site/docs/1568/1568-09-07.md","sourceDirName":"1568","slug":"/1568/1568-09-07","permalink":"/CavrianaCorr_FrontEnd/docs/1568/1568-09-07","draft":false,"unlisted":false,"editUrl":"https://github.com/Pantagrueliste/CavrianaCorr_FrontEnd/tree/main/docs/1568/1568-09-07.md","tags":[],"version":"current","frontMatter":{"title":"Guglielmo Gonzaga (1568-09-07)","expeditor":"Filippo Cavriana","addressee":"Guglielmo Gonzaga","date":"1568-09-07","placeOfOrigin":"Parigi","archiveRef":"Mantua Archivio di Stato di Mantova, Archivio Gonzaga, b654, fols. 303r-303v"},"sidebar":"tutorialSidebar","previous":{"title":"Guglielmo Gonzaga (1568-07-24)","permalink":"/CavrianaCorr_FrontEnd/docs/1568/1568-07-24"},"next":{"title":"Bartolomeo Concino (1569-01-03)","permalink":"/CavrianaCorr_FrontEnd/docs/1569/1569-01-03"}},{"id":"1569/1569-01-03","title":"Bartolomeo Concino (1569-01-03)","description":"[fol. 740r]","source":"@site/docs/1569/1569-01-03.md","sourceDirName":"1569","slug":"/1569/1569-01-03","permalink":"/CavrianaCorr_FrontEnd/docs/1569/1569-01-03","draft":false,"unlisted":false,"editUrl":"https://github.com/Pantagrueliste/CavrianaCorr_FrontEnd/tree/main/docs/1569/1569-01-03.md","tags":[],"version":"current","frontMatter":{"title":"Bartolomeo Concino (1569-01-03)","expeditor":"Filippo Cavriana","addressee":"Bartolomeo Concino","date":"1569-01-03","placeOfOrigin":"Parigi","archiveRef":"Florence Archivio di Stato di Firenze, Mediceo del Principato, 4850, fols. -"},"sidebar":"tutorialSidebar","previous":{"title":"Guglielmo Gonzaga (1568-09-07)","permalink":"/CavrianaCorr_FrontEnd/docs/1568/1568-09-07"},"next":{"title":"Jacopo Dani (1569-11-29)","permalink":"/CavrianaCorr_FrontEnd/docs/1569/1569-11-29"}},{"id":"1569/1569-11-29","title":"Jacopo Dani (1569-11-29)","description":"[fol. 436r]","source":"@site/docs/1569/1569-11-29.md","sourceDirName":"1569","slug":"/1569/1569-11-29","permalink":"/CavrianaCorr_FrontEnd/docs/1569/1569-11-29","draft":false,"unlisted":false,"editUrl":"https://github.com/Pantagrueliste/CavrianaCorr_FrontEnd/tree/main/docs/1569/1569-11-29.md","tags":[],"version":"current","frontMatter":{"title":"Jacopo Dani (1569-11-29)","expeditor":"Filippo Cavriana","addressee":"Jacopo Dani","date":"1569-11-29","placeOfOrigin":"Ancona","archiveRef":"Florence Archivio di Stato di Firenze, Mediceo del Principato, 1317, fols. 436r-436v"},"sidebar":"tutorialSidebar","previous":{"title":"Bartolomeo Concino (1569-01-03)","permalink":"/CavrianaCorr_FrontEnd/docs/1569/1569-01-03"},"next":{"title":"Bartolomeo Concino (1569-12-21)","permalink":"/CavrianaCorr_FrontEnd/docs/1569/1569-12-21"}},{"id":"1569/1569-12-21","title":"Bartolomeo Concino (1569-12-21)","description":"[fol. 57r]","source":"@site/docs/1569/1569-12-21.md","sourceDirName":"1569","slug":"/1569/1569-12-21","permalink":"/CavrianaCorr_FrontEnd/docs/1569/1569-12-21","draft":false,"unlisted":false,"editUrl":"https://github.com/Pantagrueliste/CavrianaCorr_FrontEnd/tree/main/docs/1569/1569-12-21.md","tags":[],"version":"current","frontMatter":{"title":"Bartolomeo Concino (1569-12-21)","expeditor":"Filippo Cavriana","addressee":"Bartolomeo Concino","date":"1569-12-21","placeOfOrigin":"Mantova","archiveRef":"Florence Archivio di Stato di Firenze, Mediceo del Principato, 1317, fols. -"},"sidebar":"tutorialSidebar","previous":{"title":"Jacopo Dani (1569-11-29)","permalink":"/CavrianaCorr_FrontEnd/docs/1569/1569-11-29"},"next":{"title":"Bartolomeo Concino (1570-05-20)","permalink":"/CavrianaCorr_FrontEnd/docs/1570/1570-05-20"}},{"id":"1570/1570-05-20","title":"Bartolomeo Concino (1570-05-20)","description":"[fol. 333r]","source":"@site/docs/1570/1570-05-20.md","sourceDirName":"1570","slug":"/1570/1570-05-20","permalink":"/CavrianaCorr_FrontEnd/docs/1570/1570-05-20","draft":false,"unlisted":false,"editUrl":"https://github.com/Pantagrueliste/CavrianaCorr_FrontEnd/tree/main/docs/1570/1570-05-20.md","tags":[],"version":"current","frontMatter":{"title":"Bartolomeo Concino (1570-05-20)","expeditor":"Filippo Cavriana","addressee":"Bartolomeo Concino","date":"1570-05-20","placeOfOrigin":"Parigi","archiveRef":"Florence Archivio di Stato di Firenze, Mediceo del Principato, 549, fols. 333r-336r"},"sidebar":"tutorialSidebar","previous":{"title":"Bartolomeo Concino (1569-12-21)","permalink":"/CavrianaCorr_FrontEnd/docs/1569/1569-12-21"},"next":{"title":"Bartolomeo Concino (1570-07-15)","permalink":"/CavrianaCorr_FrontEnd/docs/1570/1570-07-15"}},{"id":"1570/1570-07-15","title":"Bartolomeo Concino (1570-07-15)","description":"[fol. 219r]","source":"@site/docs/1570/1570-07-15.md","sourceDirName":"1570","slug":"/1570/1570-07-15","permalink":"/CavrianaCorr_FrontEnd/docs/1570/1570-07-15","draft":false,"unlisted":false,"editUrl":"https://github.com/Pantagrueliste/CavrianaCorr_FrontEnd/tree/main/docs/1570/1570-07-15.md","tags":[],"version":"current","frontMatter":{"title":"Bartolomeo Concino (1570-07-15)","expeditor":"Filippo Cavriana","addressee":"Bartolomeo Concino","date":"1570-07-15","placeOfOrigin":"San Germano","archiveRef":"Florence Archivio di Stato di Firenze, Mediceo del Principato, 551, fols. 219r-220v"},"sidebar":"tutorialSidebar","previous":{"title":"Bartolomeo Concino (1570-05-20)","permalink":"/CavrianaCorr_FrontEnd/docs/1570/1570-05-20"},"next":{"title":"Cosimo I de' Medici (1570-07-29)","permalink":"/CavrianaCorr_FrontEnd/docs/1570/1570-07-29-b"}},{"id":"1570/1570-07-29","title":"Unknown recipient (1570-07-29)","description":"[fol. 217r]","source":"@site/docs/1570/1570-07-29.md","sourceDirName":"1570","slug":"/1570/1570-07-29","permalink":"/CavrianaCorr_FrontEnd/docs/1570/1570-07-29","draft":false,"unlisted":false,"editUrl":"https://github.com/Pantagrueliste/CavrianaCorr_FrontEnd/tree/main/docs/1570/1570-07-29.md","tags":[],"version":"current","frontMatter":{"title":"Unknown recipient (1570-07-29)","expeditor":"Chi ella sà","addressee":"Unknown recipient","date":"1570-07-29","placeOfOrigin":"San Germano","archiveRef":"Florence Archivio di Stato di Firenze, Mediceo del Principato, 551, fols. -"},"sidebar":"tutorialSidebar","previous":{"title":"Cosimo I de' Medici (1570-07-29)","permalink":"/CavrianaCorr_FrontEnd/docs/1570/1570-07-29-b"},"next":{"title":"Bartolomeo Concino (1570-08-17)","permalink":"/CavrianaCorr_FrontEnd/docs/1570/1570-08-17"}},{"id":"1570/1570-07-29-b","title":"Cosimo I de' Medici (1570-07-29)","description":"[fol. 218r]","source":"@site/docs/1570/1570-07-29-b.md","sourceDirName":"1570","slug":"/1570/1570-07-29-b","permalink":"/CavrianaCorr_FrontEnd/docs/1570/1570-07-29-b","draft":false,"unlisted":false,"editUrl":"https://github.com/Pantagrueliste/CavrianaCorr_FrontEnd/tree/main/docs/1570/1570-07-29-b.md","tags":[],"version":"current","frontMatter":{"title":"Cosimo I de' Medici (1570-07-29)","expeditor":"Filippo Cavriana","addressee":"Cosimo I de' Medici","date":"1570-07-29","placeOfOrigin":"San Germano","archiveRef":"Florence Archivio di Stato di Firenze, Mediceo del Principato, 551, fols. -"},"sidebar":"tutorialSidebar","previous":{"title":"Bartolomeo Concino (1570-07-15)","permalink":"/CavrianaCorr_FrontEnd/docs/1570/1570-07-15"},"next":{"title":"Unknown recipient (1570-07-29)","permalink":"/CavrianaCorr_FrontEnd/docs/1570/1570-07-29"}},{"id":"1570/1570-08-17","title":"Bartolomeo Concino (1570-08-17)","description":"[fol. 1r]","source":"@site/docs/1570/1570-08-17.md","sourceDirName":"1570","slug":"/1570/1570-08-17","permalink":"/CavrianaCorr_FrontEnd/docs/1570/1570-08-17","draft":false,"unlisted":false,"editUrl":"https://github.com/Pantagrueliste/CavrianaCorr_FrontEnd/tree/main/docs/1570/1570-08-17.md","tags":[],"version":"current","frontMatter":{"title":"Bartolomeo Concino (1570-08-17)","expeditor":"Vincenzo da Castello","addressee":"Bartolomeo Concino","date":"1570-08-17","placeOfOrigin":"Parigi","archiveRef":"Florence Archivio di Stato di Firenze, Mediceo del Principato, 4726a, fols. -"},"sidebar":"tutorialSidebar","previous":{"title":"Unknown recipient (1570-07-29)","permalink":"/CavrianaCorr_FrontEnd/docs/1570/1570-07-29"},"next":{"title":"Bartolomeo Concino (1570-09-01)","permalink":"/CavrianaCorr_FrontEnd/docs/1570/1570-09-01"}},{"id":"1570/1570-09-01","title":"Bartolomeo Concino (1570-09-01)","description":"[fol. 236r]","source":"@site/docs/1570/1570-09-01.md","sourceDirName":"1570","slug":"/1570/1570-09-01","permalink":"/CavrianaCorr_FrontEnd/docs/1570/1570-09-01","draft":false,"unlisted":false,"editUrl":"https://github.com/Pantagrueliste/CavrianaCorr_FrontEnd/tree/main/docs/1570/1570-09-01.md","tags":[],"version":"current","frontMatter":{"title":"Bartolomeo Concino (1570-09-01)","expeditor":"Vincenzo da Castello","addressee":"Bartolomeo Concino","date":"1570-09-01","placeOfOrigin":"Parigi","archiveRef":"Florence Archivio di Stato di Firenze, Mediceo del Principato, 551, fols. 236r-239r"},"sidebar":"tutorialSidebar","previous":{"title":"Bartolomeo Concino (1570-08-17)","permalink":"/CavrianaCorr_FrontEnd/docs/1570/1570-08-17"},"next":{"title":"Cosimo I de' Medici (1570-09-11)","permalink":"/CavrianaCorr_FrontEnd/docs/1570/1570-09-11"}},{"id":"1570/1570-09-11","title":"Cosimo I de' Medici (1570-09-11)","description":"[fol. 3r]","source":"@site/docs/1570/1570-09-11.md","sourceDirName":"1570","slug":"/1570/1570-09-11","permalink":"/CavrianaCorr_FrontEnd/docs/1570/1570-09-11","draft":false,"unlisted":false,"editUrl":"https://github.com/Pantagrueliste/CavrianaCorr_FrontEnd/tree/main/docs/1570/1570-09-11.md","tags":[],"version":"current","frontMatter":{"title":"Cosimo I de' Medici (1570-09-11)","expeditor":"Filippo Cavriana","addressee":"Cosimo I de' Medici","date":"1570-09-11","placeOfOrigin":"Parigi","archiveRef":"Florence Archivio di Stato di Firenze, Mediceo del Principato, 554, fols. -"},"sidebar":"tutorialSidebar","previous":{"title":"Bartolomeo Concino (1570-09-01)","permalink":"/CavrianaCorr_FrontEnd/docs/1570/1570-09-01"},"next":{"title":"Cosimo I de' Medici (1570-09-14)","permalink":"/CavrianaCorr_FrontEnd/docs/1570/1570-09-14"}},{"id":"1570/1570-09-14","title":"Cosimo I de' Medici (1570-09-14)","description":"[fol. 2r]","source":"@site/docs/1570/1570-09-14.md","sourceDirName":"1570","slug":"/1570/1570-09-14","permalink":"/CavrianaCorr_FrontEnd/docs/1570/1570-09-14","draft":false,"unlisted":false,"editUrl":"https://github.com/Pantagrueliste/CavrianaCorr_FrontEnd/tree/main/docs/1570/1570-09-14.md","tags":[],"version":"current","frontMatter":{"title":"Cosimo I de' Medici (1570-09-14)","expeditor":"Filippo Cavriana","addressee":"Cosimo I de' Medici","date":"1570-09-14","placeOfOrigin":"Parigi","archiveRef":"Florence Archivio di Stato di Firenze, Mediceo del Principato, 562, fols. -"},"sidebar":"tutorialSidebar","previous":{"title":"Cosimo I de' Medici (1570-09-11)","permalink":"/CavrianaCorr_FrontEnd/docs/1570/1570-09-11"},"next":{"title":"Bartolomeo Concino (1570-10-03)","permalink":"/CavrianaCorr_FrontEnd/docs/1570/1570-10-03"}},{"id":"1570/1570-10-03","title":"Bartolomeo Concino (1570-10-03)","description":"[fol. 331r]","source":"@site/docs/1570/1570-10-03.md","sourceDirName":"1570","slug":"/1570/1570-10-03","permalink":"/CavrianaCorr_FrontEnd/docs/1570/1570-10-03","draft":false,"unlisted":false,"editUrl":"https://github.com/Pantagrueliste/CavrianaCorr_FrontEnd/tree/main/docs/1570/1570-10-03.md","tags":[],"version":"current","frontMatter":{"title":"Bartolomeo Concino (1570-10-03)","expeditor":"Filippo Cavriana","addressee":"Bartolomeo Concino","date":"1570-10-03","placeOfOrigin":"Parigi","archiveRef":"Florence Archivio di Stato di Firenze, Mediceo del Principato, 555, fols. -"},"sidebar":"tutorialSidebar","previous":{"title":"Cosimo I de' Medici (1570-09-14)","permalink":"/CavrianaCorr_FrontEnd/docs/1570/1570-09-14"},"next":{"title":"Cosimo I de' Medici (1570-10-11)","permalink":"/CavrianaCorr_FrontEnd/docs/1570/1570-10-11"}},{"id":"1570/1570-10-11","title":"Cosimo I de' Medici (1570-10-11)","description":"[fol. 3r]","source":"@site/docs/1570/1570-10-11.md","sourceDirName":"1570","slug":"/1570/1570-10-11","permalink":"/CavrianaCorr_FrontEnd/docs/1570/1570-10-11","draft":false,"unlisted":false,"editUrl":"https://github.com/Pantagrueliste/CavrianaCorr_FrontEnd/tree/main/docs/1570/1570-10-11.md","tags":[],"version":"current","frontMatter":{"title":"Cosimo I de' Medici (1570-10-11)","expeditor":"Filippo Cavriana","addressee":"Cosimo I de' Medici","date":"1570-10-11","placeOfOrigin":"Parigi","archiveRef":"Florence Archivio di Stato di Firenze, Mediceo del Principato, 562, fols. -"},"sidebar":"tutorialSidebar","previous":{"title":"Bartolomeo Concino (1570-10-03)","permalink":"/CavrianaCorr_FrontEnd/docs/1570/1570-10-03"},"next":{"title":"Cosimo I de' Medici (1570-11-02)","permalink":"/CavrianaCorr_FrontEnd/docs/1570/1570-11-02-a"}},{"id":"1570/1570-11-02","title":"Cosimo I de' Medici (1570-11-02)","description":"[fol. 47r]","source":"@site/docs/1570/1570-11-02.md","sourceDirName":"1570","slug":"/1570/1570-11-02","permalink":"/CavrianaCorr_FrontEnd/docs/1570/1570-11-02","draft":false,"unlisted":false,"editUrl":"https://github.com/Pantagrueliste/CavrianaCorr_FrontEnd/tree/main/docs/1570/1570-11-02.md","tags":[],"version":"current","frontMatter":{"title":"Cosimo I de' Medici (1570-11-02)","expeditor":"Filippo Cavriana","addressee":"Cosimo I de' Medici","date":"1570-11-02","placeOfOrigin":"San Germano di Pre","archiveRef":"Florence Archivio di Stato di Firenze, Mediceo del Principato, 562, fols. -"},"sidebar":"tutorialSidebar","previous":{"title":"Cosimo I de' Medici (1570-11-02)","permalink":"/CavrianaCorr_FrontEnd/docs/1570/1570-11-02-c"},"next":{"title":"Bartolomeo Concino (1570-11-09)","permalink":"/CavrianaCorr_FrontEnd/docs/1570/1570-11-09"}},{"id":"1570/1570-11-02-a","title":"Cosimo I de' Medici (1570-11-02)","description":"[fol. 47r]","source":"@site/docs/1570/1570-11-02-a.md","sourceDirName":"1570","slug":"/1570/1570-11-02-a","permalink":"/CavrianaCorr_FrontEnd/docs/1570/1570-11-02-a","draft":false,"unlisted":false,"editUrl":"https://github.com/Pantagrueliste/CavrianaCorr_FrontEnd/tree/main/docs/1570/1570-11-02-a.md","tags":[],"version":"current","frontMatter":{"title":"Cosimo I de' Medici (1570-11-02)","expeditor":"Filippo Cavriana","addressee":"Cosimo I de' Medici","date":"1570-11-02","placeOfOrigin":"Saint-Germain-des-Prés","archiveRef":"Florence Archivio di Stato di Firenze, Mediceo del Principato, 562, fols. -"},"sidebar":"tutorialSidebar","previous":{"title":"Cosimo I de' Medici (1570-10-11)","permalink":"/CavrianaCorr_FrontEnd/docs/1570/1570-10-11"},"next":{"title":"Bartolomeo Concino (1570-11-02)","permalink":"/CavrianaCorr_FrontEnd/docs/1570/1570-11-02-b"}},{"id":"1570/1570-11-02-b","title":"Bartolomeo Concino (1570-11-02)","description":"[fol. 336r]","source":"@site/docs/1570/1570-11-02-b.md","sourceDirName":"1570","slug":"/1570/1570-11-02-b","permalink":"/CavrianaCorr_FrontEnd/docs/1570/1570-11-02-b","draft":false,"unlisted":false,"editUrl":"https://github.com/Pantagrueliste/CavrianaCorr_FrontEnd/tree/main/docs/1570/1570-11-02-b.md","tags":[],"version":"current","frontMatter":{"title":"Bartolomeo Concino (1570-11-02)","expeditor":"Filippo Cavriana","addressee":"Bartolomeo Concino","date":"1570-11-02","placeOfOrigin":"Saint-Germain-des-Prés","archiveRef":"Florence Archivio di Stato di Firenze, Mediceo del Principato, 555bis, fols. 336r-336v"},"sidebar":"tutorialSidebar","previous":{"title":"Cosimo I de' Medici (1570-11-02)","permalink":"/CavrianaCorr_FrontEnd/docs/1570/1570-11-02-a"},"next":{"title":"Cosimo I de' Medici (1570-11-02)","permalink":"/CavrianaCorr_FrontEnd/docs/1570/1570-11-02-c"}},{"id":"1570/1570-11-02-c","title":"Cosimo I de' Medici (1570-11-02)","description":"[fol. 336r]","source":"@site/docs/1570/1570-11-02-c.md","sourceDirName":"1570","slug":"/1570/1570-11-02-c","permalink":"/CavrianaCorr_FrontEnd/docs/1570/1570-11-02-c","draft":false,"unlisted":false,"editUrl":"https://github.com/Pantagrueliste/CavrianaCorr_FrontEnd/tree/main/docs/1570/1570-11-02-c.md","tags":[],"version":"current","frontMatter":{"title":"Cosimo I de' Medici (1570-11-02)","expeditor":"Filippo Cavriana","addressee":"Cosimo I de' Medici","date":"1570-11-02","placeOfOrigin":"Saint-Germain-des-Prés","archiveRef":"Florence Archivio di Stato di Firenze, Mediceo del Principato, 555, fols. 336r-336v"},"sidebar":"tutorialSidebar","previous":{"title":"Bartolomeo Concino (1570-11-02)","permalink":"/CavrianaCorr_FrontEnd/docs/1570/1570-11-02-b"},"next":{"title":"Cosimo I de' Medici (1570-11-02)","permalink":"/CavrianaCorr_FrontEnd/docs/1570/1570-11-02"}},{"id":"1570/1570-11-09","title":"Bartolomeo Concino (1570-11-09)","description":"[fol. 343r]","source":"@site/docs/1570/1570-11-09.md","sourceDirName":"1570","slug":"/1570/1570-11-09","permalink":"/CavrianaCorr_FrontEnd/docs/1570/1570-11-09","draft":false,"unlisted":false,"editUrl":"https://github.com/Pantagrueliste/CavrianaCorr_FrontEnd/tree/main/docs/1570/1570-11-09.md","tags":[],"version":"current","frontMatter":{"title":"Bartolomeo Concino (1570-11-09)","expeditor":"Filippo Cavriana","addressee":"Bartolomeo Concino","date":"1570-11-09","placeOfOrigin":"Parigi","archiveRef":"Firenze Archivio di Stato di Firenze, Mediceo del Principato, 555, fols. -"},"sidebar":"tutorialSidebar","previous":{"title":"Cosimo I de' Medici (1570-11-02)","permalink":"/CavrianaCorr_FrontEnd/docs/1570/1570-11-02"},"next":{"title":"Bartolomeo Concino (1571-01-14)","permalink":"/CavrianaCorr_FrontEnd/docs/1571/1571-01-14"}},{"id":"1571/1571-01-14","title":"Bartolomeo Concino (1571-01-14)","description":"[fol. 7r]","source":"@site/docs/1571/1571-01-14.md","sourceDirName":"1571","slug":"/1571/1571-01-14","permalink":"/CavrianaCorr_FrontEnd/docs/1571/1571-01-14","draft":false,"unlisted":false,"editUrl":"https://github.com/Pantagrueliste/CavrianaCorr_FrontEnd/tree/main/docs/1571/1571-01-14.md","tags":[],"version":"current","frontMatter":{"title":"Bartolomeo Concino (1571-01-14)","expeditor":"Filippo Cavriana","addressee":"Bartolomeo Concino","date":"1571-01-14","placeOfOrigin":"Parigi","archiveRef":"Firenze Archivio di Stato di Firenze, Mediceo del Principato, 4726a, fols. 7r-10v"},"sidebar":"tutorialSidebar","previous":{"title":"Bartolomeo Concino (1570-11-09)","permalink":"/CavrianaCorr_FrontEnd/docs/1570/1570-11-09"},"next":{"title":"Cosimo I de' Medici (1571-04-18)","permalink":"/CavrianaCorr_FrontEnd/docs/1571/1571-04-18"}},{"id":"1571/1571-04-18","title":"Cosimo I de' Medici (1571-04-18)","description":"[fol. 130r]","source":"@site/docs/1571/1571-04-18.md","sourceDirName":"1571","slug":"/1571/1571-04-18","permalink":"/CavrianaCorr_FrontEnd/docs/1571/1571-04-18","draft":false,"unlisted":false,"editUrl":"https://github.com/Pantagrueliste/CavrianaCorr_FrontEnd/tree/main/docs/1571/1571-04-18.md","tags":[],"version":"current","frontMatter":{"title":"Cosimo I de' Medici (1571-04-18)","expeditor":"Filippo Cavriana","addressee":"Cosimo I de' Medici","date":"1571-04-18","placeOfOrigin":"Parigi","archiveRef":"Florence Archivio di Stato di Firenze, Mediceo del Principato, 554, fols. -"},"sidebar":"tutorialSidebar","previous":{"title":"Bartolomeo Concino (1571-01-14)","permalink":"/CavrianaCorr_FrontEnd/docs/1571/1571-01-14"},"next":{"title":"Duke of Mantua (1571-07-15)","permalink":"/CavrianaCorr_FrontEnd/docs/1571/1571-07-15"}},{"id":"1571/1571-07-15","title":"Duke of Mantua (1571-07-15)","description":"[fol. 336r]","source":"@site/docs/1571/1571-07-15.md","sourceDirName":"1571","slug":"/1571/1571-07-15","permalink":"/CavrianaCorr_FrontEnd/docs/1571/1571-07-15","draft":false,"unlisted":false,"editUrl":"https://github.com/Pantagrueliste/CavrianaCorr_FrontEnd/tree/main/docs/1571/1571-07-15.md","tags":[],"version":"current","frontMatter":{"title":"Duke of Mantua (1571-07-15)","expeditor":"Filippo Cavriana","addressee":"Duke of Mantua","date":"1571-07-15","placeOfOrigin":"Bagni di Lucca","archiveRef":"Mantova Archivio di Stato di Mantova, Archivio Gonzaga, b654, fols. -"},"sidebar":"tutorialSidebar","previous":{"title":"Cosimo I de' Medici (1571-04-18)","permalink":"/CavrianaCorr_FrontEnd/docs/1571/1571-04-18"}},{"id":"intro","title":"Introduction","description":"This digital edition presents the correspondence of Filippo Cavriana, a physician, diplomat, and scholar active in the late 16th century.","source":"@site/docs/intro.md","sourceDirName":".","slug":"/intro","permalink":"/CavrianaCorr_FrontEnd/docs/intro","draft":false,"unlisted":false,"editUrl":"https://github.com/Pantagrueliste/CavrianaCorr_FrontEnd/tree/main/docs/intro.md","tags":[],"version":"current","sidebarPosition":1,"frontMatter":{"sidebar_position":1,"title":"Introduction"},"sidebar":"tutorialSidebar","next":{"title":"Guglielmo Gonzaga (1568-04-06)","permalink":"/CavrianaCorr_FrontEnd/docs/1568/1568-04-06"}}],"drafts":[],"sidebars":{"tutorialSidebar":[{"type":"doc","id":"intro"},{"type":"category","label":"1568","collapsible":true,"collapsed":true,"items":[{"type":"doc","id":"1568/1568-04-06"},{"type":"doc","id":"1568/1568-04-28"},{"type":"doc","id":"1568/1568-05-04"},{"type":"doc","id":"1568/1568-05-05"},{"type":"doc","id":"1568/1568-05-28"},{"type":"doc","id":"1568/1568-06-09"},{"type":"doc","id":"1568/1568-07-03"},{"type":"doc","id":"1568/1568-07-24"},{"type":"doc","id":"1568/1568-09-07"}]},{"type":"category","label":"1569","collapsible":true,"collapsed":true,"items":[{"type":"doc","id":"1569/1569-01-03"},{"type":"doc","id":"1569/1569-11-29"},{"type":"doc","id":"1569/1569-12-21"}]},{"type":"category","label":"1570","collapsible":true,"collapsed":true,"items":[{"type":"doc","id":"1570/1570-05-20"},{"type":"doc","id":"1570/1570-07-15"},{"type":"doc","id":"1570/1570-07-29-b"},{"type":"doc","id":"1570/1570-07-29"},{"type":"doc","id":"1570/1570-08-17"},{"type":"doc","id":"1570/1570-09-01"},{"type":"doc","id":"1570/1570-09-11"},{"type":"doc","id":"1570/1570-09-14"},{"type":"doc","id":"1570/1570-10-03"},{"type":"doc","id":"1570/1570-10-11"},{"type":"doc","id":"1570/1570-11-02-a"},{"type":"doc","id":"1570/1570-11-02-b"},{"type":"doc","id":"1570/1570-11-02-c"},{"type":"doc","id":"1570/1570-11-02"},{"type":"doc","id":"1570/1570-11-09"}]},{"type":"category","label":"1571","collapsible":true,"collapsed":true,"items":[{"type":"doc","id":"1571/1571-01-14"},{"type":"doc","id":"1571/1571-04-18"},{"type":"doc","id":"1571/1571-07-15"}]}]}}]}},"docusaurus-plugin-content-blog":{"default":{"blogSidebarTitle":"Recent posts","blogPosts":[{"id":"welcome","metadata":{"permalink":"/CavrianaCorr_FrontEnd/blog/welcome","editUrl":"https://github.com/Pantagrueliste/CavrianaCorr_FrontEnd/tree/main/blog/2021-08-26-welcome/index.md","source":"@site/blog/2021-08-26-welcome/index.md","title":"Welcome","description":"Docusaurus blogging features are powered by the blog plugin.","date":"2021-08-26T00:00:00.000Z","tags":[{"inline":true,"label":"facebook","permalink":"/CavrianaCorr_FrontEnd/blog/tags/facebook"},{"inline":true,"label":"hello","permalink":"/CavrianaCorr_FrontEnd/blog/tags/hello"},{"inline":true,"label":"docusaurus","permalink":"/CavrianaCorr_FrontEnd/blog/tags/docusaurus"}],"readingTime":0.405,"hasTruncateMarker":false,"authors":[{"name":"Sébastien Lorber","title":"Docusaurus maintainer","url":"https://sebastienlorber.com","imageURL":"https://github.com/slorber.png","key":"slorber","page":null},{"name":"Yangshun Tay","title":"Front End Engineer @ Facebook","url":"https://github.com/yangshun","imageURL":"https://github.com/yangshun.png","key":"yangshun","page":null}],"frontMatter":{"slug":"welcome","title":"Welcome","authors":["slorber","yangshun"],"tags":["facebook","hello","docusaurus"]},"unlisted":false,"nextItem":{"title":"MDX Blog Post","permalink":"/CavrianaCorr_FrontEnd/blog/mdx-blog-post"}},"content":"[Docusaurus blogging features](https://docusaurus.io/docs/blog) are powered by the [blog plugin](https://docusaurus.io/docs/api/plugins/@docusaurus/plugin-content-blog).\n\nSimply add Markdown files (or folders) to the `blog` directory.\n\nRegular blog authors can be added to `authors.yml`.\n\nThe blog post date can be extracted from filenames, such as:\n\n- `2019-05-30-welcome.md`\n- `2019-05-30-welcome/index.md`\n\nA blog post folder can be convenient to co-locate blog post images:\n\n![Docusaurus Plushie](./docusaurus-plushie-banner.jpeg)\n\nThe blog supports tags as well!\n\n**And if you don't want a blog**: just delete this directory, and use `blog: false` in your Docusaurus config."},{"id":"mdx-blog-post","metadata":{"permalink":"/CavrianaCorr_FrontEnd/blog/mdx-blog-post","editUrl":"https://github.com/Pantagrueliste/CavrianaCorr_FrontEnd/tree/main/blog/2021-08-01-mdx-blog-post.mdx","source":"@site/blog/2021-08-01-mdx-blog-post.mdx","title":"MDX Blog Post","description":"Blog posts support Docusaurus Markdown features, such as MDX.","date":"2021-08-01T00:00:00.000Z","tags":[{"inline":true,"label":"docusaurus","permalink":"/CavrianaCorr_FrontEnd/blog/tags/docusaurus"}],"readingTime":0.175,"hasTruncateMarker":false,"authors":[{"name":"Sébastien Lorber","title":"Docusaurus maintainer","url":"https://sebastienlorber.com","imageURL":"https://github.com/slorber.png","key":"slorber","page":null}],"frontMatter":{"slug":"mdx-blog-post","title":"MDX Blog Post","authors":["slorber"],"tags":["docusaurus"]},"unlisted":false,"prevItem":{"title":"Welcome","permalink":"/CavrianaCorr_FrontEnd/blog/welcome"},"nextItem":{"title":"Long Blog Post","permalink":"/CavrianaCorr_FrontEnd/blog/long-blog-post"}},"content":"Blog posts support [Docusaurus Markdown features](https://docusaurus.io/docs/markdown-features), such as [MDX](https://mdxjs.com/).\n\n:::tip\n\nUse the power of React to create interactive blog posts.\n\n```js\n<button onClick={() => alert('button clicked!')}>Click me!</button>\n```\n\n<button onClick={() => alert('button clicked!')}>Click me!</button>\n\n:::"},{"id":"long-blog-post","metadata":{"permalink":"/CavrianaCorr_FrontEnd/blog/long-blog-post","editUrl":"https://github.com/Pantagrueliste/CavrianaCorr_FrontEnd/tree/main/blog/2019-05-29-long-blog-post.md","source":"@site/blog/2019-05-29-long-blog-post.md","title":"Long Blog Post","description":"This is the summary of a very long blog post,","date":"2019-05-29T00:00:00.000Z","tags":[{"inline":true,"label":"hello","permalink":"/CavrianaCorr_FrontEnd/blog/tags/hello"},{"inline":true,"label":"docusaurus","permalink":"/CavrianaCorr_FrontEnd/blog/tags/docusaurus"}],"readingTime":2.05,"hasTruncateMarker":true,"authors":[{"name":"Endilie Yacop Sucipto","title":"Maintainer of Docusaurus","url":"https://github.com/endiliey","imageURL":"https://github.com/endiliey.png","key":"endi","page":null}],"frontMatter":{"slug":"long-blog-post","title":"Long Blog Post","authors":"endi","tags":["hello","docusaurus"]},"unlisted":false,"prevItem":{"title":"MDX Blog Post","permalink":"/CavrianaCorr_FrontEnd/blog/mdx-blog-post"},"nextItem":{"title":"First Blog Post","permalink":"/CavrianaCorr_FrontEnd/blog/first-blog-post"}},"content":"This is the summary of a very long blog post,\n\nUse a `<!--` `truncate` `-->` comment to limit blog post size in the list view.\n\n<!--truncate-->\n\nLorem ipsum dolor sit amet, consectetur adipiscing elit. Pellentesque elementum dignissim ultricies. Fusce rhoncus ipsum tempor eros aliquam consequat. Lorem ipsum dolor sit amet\n\nLorem ipsum dolor sit amet, consectetur adipiscing elit. Pellentesque elementum dignissim ultricies. Fusce rhoncus ipsum tempor eros aliquam consequat. Lorem ipsum dolor sit amet\n\nLorem ipsum dolor sit amet, consectetur adipiscing elit. Pellentesque elementum dignissim ultricies. Fusce rhoncus ipsum tempor eros aliquam consequat. Lorem ipsum dolor sit amet\n\nLorem ipsum dolor sit amet, consectetur adipiscing elit. Pellentesque elementum dignissim ultricies. Fusce rhoncus ipsum tempor eros aliquam consequat. Lorem ipsum dolor sit amet\n\nLorem ipsum dolor sit amet, consectetur adipiscing elit. Pellentesque elementum dignissim ultricies. Fusce rhoncus ipsum tempor eros aliquam consequat. Lorem ipsum dolor sit amet\n\nLorem ipsum dolor sit amet, consectetur adipiscing elit. Pellentesque elementum dignissim ultricies. Fusce rhoncus ipsum tempor eros aliquam consequat. Lorem ipsum dolor sit amet\n\nLorem ipsum dolor sit amet, consectetur adipiscing elit. Pellentesque elementum dignissim ultricies. Fusce rhoncus ipsum tempor eros aliquam consequat. Lorem ipsum dolor sit amet\n\nLorem ipsum dolor sit amet, consectetur adipiscing elit. Pellentesque elementum dignissim ultricies. Fusce rhoncus ipsum tempor eros aliquam consequat. Lorem ipsum dolor sit amet\n\nLorem ipsum dolor sit amet, consectetur adipiscing elit. Pellentesque elementum dignissim ultricies. Fusce rhoncus ipsum tempor eros aliquam consequat. Lorem ipsum dolor sit amet\n\nLorem ipsum dolor sit amet, consectetur adipiscing elit. Pellentesque elementum dignissim ultricies. Fusce rhoncus ipsum tempor eros aliquam consequat. Lorem ipsum dolor sit amet\n\nLorem ipsum dolor sit amet, consectetur adipiscing elit. Pellentesque elementum dignissim ultricies. Fusce rhoncus ipsum tempor eros aliquam consequat. Lorem ipsum dolor sit amet\n\nLorem ipsum dolor sit amet, consectetur adipiscing elit. Pellentesque elementum dignissim ultricies. Fusce rhoncus ipsum tempor eros aliquam consequat. Lorem ipsum dolor sit amet\n\nLorem ipsum dolor sit amet, consectetur adipiscing elit. Pellentesque elementum dignissim ultricies. Fusce rhoncus ipsum tempor eros aliquam consequat. Lorem ipsum dolor sit amet\n\nLorem ipsum dolor sit amet, consectetur adipiscing elit. Pellentesque elementum dignissim ultricies. Fusce rhoncus ipsum tempor eros aliquam consequat. Lorem ipsum dolor sit amet\n\nLorem ipsum dolor sit amet, consectetur adipiscing elit. Pellentesque elementum dignissim ultricies. Fusce rhoncus ipsum tempor eros aliquam consequat. Lorem ipsum dolor sit amet\n\nLorem ipsum dolor sit amet, consectetur adipiscing elit. Pellentesque elementum dignissim ultricies. Fusce rhoncus ipsum tempor eros aliquam consequat. Lorem ipsum dolor sit amet"},{"id":"first-blog-post","metadata":{"permalink":"/CavrianaCorr_FrontEnd/blog/first-blog-post","editUrl":"https://github.com/Pantagrueliste/CavrianaCorr_FrontEnd/tree/main/blog/2019-05-28-first-blog-post.md","source":"@site/blog/2019-05-28-first-blog-post.md","title":"First Blog Post","description":"Lorem ipsum dolor sit amet, consectetur adipiscing elit. Pellentesque elementum dignissim ultricies. Fusce rhoncus ipsum tempor eros aliquam consequat. Lorem ipsum dolor sit amet","date":"2019-05-28T00:00:00.000Z","tags":[{"inline":true,"label":"hola","permalink":"/CavrianaCorr_FrontEnd/blog/tags/hola"},{"inline":true,"label":"docusaurus","permalink":"/CavrianaCorr_FrontEnd/blog/tags/docusaurus"}],"readingTime":0.12,"hasTruncateMarker":false,"authors":[{"name":"Gao Wei","title":"Docusaurus Core Team","url":"https://github.com/wgao19","image_url":"https://github.com/wgao19.png","imageURL":"https://github.com/wgao19.png","socials":{},"key":null,"page":null}],"frontMatter":{"slug":"first-blog-post","title":"First Blog Post","authors":{"name":"Gao Wei","title":"Docusaurus Core Team","url":"https://github.com/wgao19","image_url":"https://github.com/wgao19.png","imageURL":"https://github.com/wgao19.png"},"tags":["hola","docusaurus"]},"unlisted":false,"prevItem":{"title":"Long Blog Post","permalink":"/CavrianaCorr_FrontEnd/blog/long-blog-post"}},"content":"Lorem ipsum dolor sit amet, consectetur adipiscing elit. Pellentesque elementum dignissim ultricies. Fusce rhoncus ipsum tempor eros aliquam consequat. Lorem ipsum dolor sit amet"}],"blogListPaginated":[{"items":["welcome","mdx-blog-post","long-blog-post","first-blog-post"],"metadata":{"permalink":"/CavrianaCorr_FrontEnd/blog","page":1,"postsPerPage":10,"totalPages":1,"totalCount":4,"blogDescription":"Blog","blogTitle":"Blog"}}],"blogTags":{"/CavrianaCorr_FrontEnd/blog/tags/facebook":{"inline":true,"label":"facebook","permalink":"/CavrianaCorr_FrontEnd/blog/tags/facebook","items":["welcome"],"pages":[{"items":["welcome"],"metadata":{"permalink":"/CavrianaCorr_FrontEnd/blog/tags/facebook","page":1,"postsPerPage":10,"totalPages":1,"totalCount":1,"blogDescription":"Blog","blogTitle":"Blog"}}],"unlisted":false},"/CavrianaCorr_FrontEnd/blog/tags/hello":{"inline":true,"label":"hello","permalink":"/CavrianaCorr_FrontEnd/blog/tags/hello","items":["welcome","long-blog-post"],"pages":[{"items":["welcome","long-blog-post"],"metadata":{"permalink":"/CavrianaCorr_FrontEnd/blog/tags/hello","page":1,"postsPerPage":10,"totalPages":1,"totalCount":2,"blogDescription":"Blog","blogTitle":"Blog"}}],"unlisted":false},"/CavrianaCorr_FrontEnd/blog/tags/docusaurus":{"inline":true,"label":"docusaurus","permalink":"/CavrianaCorr_FrontEnd/blog/tags/docusaurus","items":["welcome","mdx-blog-post","long-blog-post","first-blog-post"],"pages":[{"items":["welcome","mdx-blog-post","long-blog-post","first-blog-post"],"metadata":{"permalink":"/CavrianaCorr_FrontEnd/blog/tags/docusaurus","page":1,"postsPerPage":10,"totalPages":1,"totalCount":4,"blogDescription":"Blog","blogTitle":"Blog"}}],"unlisted":false},"/CavrianaCorr_FrontEnd/blog/tags/hola":{"inline":true,"label":"hola","permalink":"/CavrianaCorr_FrontEnd/blog/tags/hola","items":["first-blog-post"],"pages":[{"items":["first-blog-post"],"metadata":{"permalink":"/CavrianaCorr_FrontEnd/blog/tags/hola","page":1,"postsPerPage":10,"totalPages":1,"totalCount":1,"blogDescription":"Blog","blogTitle":"Blog"}}],"unlisted":false}},"blogTagsListPath":"/CavrianaCorr_FrontEnd/blog/tags","authorsMap":{"endi":{"name":"Endilie Yacop Sucipto","title":"Maintainer of Docusaurus","url":"https://github.com/endiliey","imageURL":"https://github.com/endiliey.png","key":"endi","page":null},"yangshun":{"name":"Yangshun Tay","title":"Front End Engineer @ Facebook","url":"https://github.com/yangshun","imageURL":"https://github.com/yangshun.png","key":"yangshun","page":null},"slorber":{"name":"Sébastien Lorber","title":"Docusaurus maintainer","url":"https://sebastienlorber.com","imageURL":"https://github.com/slorber.png","key":"slorber","page":null},"cgodbarge":{"name":"Clément Godbarge","title":"Editor","url":"https://www.clementgodbarge.com","imageURL":"https://clementgodbarge.com/authors/admin/avatar_huc514799c23ece07f5cfd891842101f8a_857524_270x270_fill_q90_h2_lanczos_center_2.webp","key":"cgodbarge","page":null}}}},"docusaurus-plugin-content-pages":{"default":[{"type":"jsx","permalink":"/CavrianaCorr_FrontEnd/","source":"@site/src/pages/index.js"},{"type":"mdx","permalink":"/CavrianaCorr_FrontEnd/markdown-page","source":"@site/src/pages/markdown-page.md","title":"Markdown page example","description":"You don't need React to write simple standalone pages.","frontMatter":{"title":"Markdown page example"},"unlisted":false}]},"docusaurus-plugin-debug":{},"docusaurus-plugin-svgr":{},"docusaurus-theme-classic":{},"docusaurus-bootstrap-plugin":{},"docusaurus-mdx-fallback-plugin":{}}}